faust_prometheus/__init__.py
faust_prometheus/collectors.py
faust_prometheus/exporter.py
faust_prometheus_exporter-0.1.9.dist-info/LICENSE
faust_prometheus_exporter-0.1.9.dist-info/METADATA
faust_prometheus_exporter-0.1.9.dist-info/WHEEL
faust_prometheus_exporter-0.1.9.dist-info/RECORD
