Metadata-Version: 2.1
Name: faust-prometheus-exporter
Version: 0.1.9
Summary: Module for exporting monitoring values for Prometheus
Home-page: https://gitlab.com/rocshers/python/faust-prometheus
License: MIT
Author: irocshers
Author-email: develop.iam@rocshers.com
Requires-Python: >=3.8,<4
Classifier: Intended Audience :: Developers
Classifier: Intended Audience :: Information Technology
Classifier: Intended Audience :: System Administrators
Classifier: License :: OSI Approved :: MIT License
Classifier: Programming Language :: Python
Classifier: Programming Language :: Python :: 3
Classifier: Programming Language :: Python :: 3.8
Classifier: Programming Language :: Python :: 3.9
Classifier: Programming Language :: Python :: 3.10
Classifier: Programming Language :: Python :: 3.11
Classifier: Programming Language :: Python :: 3 :: Only
Classifier: Topic :: Software Development :: Libraries
Classifier: Topic :: Software Development :: Libraries :: Python Modules
Classifier: Topic :: System :: Archiving :: Packaging
Classifier: Topic :: System :: Software Distribution
Requires-Dist: faust-streaming (<1)
Requires-Dist: prometheus-client (<1)
Requires-Dist: prometheus-client-utils (>=0.1.3,<0.2.0)
Project-URL: Repository, https://gitlab.com/rocshers/python/faust-prometheus
